polars_strsim-0.2.5.dist-info/METADATA
polars_strsim-0.2.5.dist-info/WHEEL
polars_strsim-0.2.5.dist-info/licenses/LICENSE
polars_strsim.libs/libgcc_s-b5472b99.so.1
polars_strsim/py.typed
polars_strsim/utils.py
polars_strsim/__init__.py
polars_strsim/polars_strsim.abi3.so
polars_strsim-0.2.5.dist-info/RECORD
