Metadata-Version: 2.4
Name: polars-strsim
Version: 0.2.5
Classifier: Development Status :: 4 - Beta
Classifier: Intended Audience :: Developers
Classifier: Intended Audience :: Science/Research
Classifier: License :: OSI Approved :: MIT License
Classifier: Operating System :: OS Independent
Classifier: Programming Language :: Python :: 3
Classifier: Programming Language :: Python :: 3.10
Classifier: Programming Language :: Python :: 3.11
Classifier: Programming Language :: Python :: 3.12
Classifier: Programming Language :: Python :: 3.8
Classifier: Programming Language :: Python :: 3.9
Classifier: Programming Language :: Python :: 3 :: Only
Classifier: Programming Language :: Python :: Implementation :: CPython
Classifier: Programming Language :: Python :: Implementation :: PyPy
Classifier: Programming Language :: Rust
Requires-Dist: polars>=1.0,<2.0
License-File: LICENSE
Summary: Polars extension for string similarity
Keywords: polars-extension,string-similarity
Author: Jeremy Foxcroft
Requires-Python: >=3.8
Project-URL: Repository, https://github.com/foxcroftjn/polars-strsim
Project-URL: Issues, https://github.com/foxcroftjn/polars-strsim/issues
